<?xml version="1.0" encoding="UTF-8"?>
<node>
<version>6</version>
<dict>
  <key>title</key><string>Active Directory Management</string>
  <key>nodeid</key><string>338f1caf-7dbd-4752-9cfe-08249fa6d1d8</string>
  <key>modified_time</key><integer>1597781624</integer>
  <key>version</key><integer>6</integer>
  <key>content_type</key><string>text/xhtml+xml</string>
  <key>created_time</key><integer>1597763219</integer>
  <key>info_sort_dir</key><integer>1</integer>
  <key>order</key><integer>3</integer>
  <key>info_sort</key><string>order</string>
</dict>
</node>
